{
    "price": 5023.2,
    "rsi": 63.36,
    "deviation": 0.24,
    "correlation": "Error",
    "score_1h": -20,
    "score_4h": -21,
    "is_golden": false,
    "is_death": false,
    "vol_spike": false,
    "trend_4h": "上昇",
    "resistance": 5042.8,
    "support": 4867.0,
    "cisd_high": 4926.3,
    "cisd_low": 4975.5,
    "vacuum_zones": [],
    "is_synced": false,
    "sync_dir": "下落",
    "status": "静観",
    "reason": "明確なシグナルなし。DXY相関(0.00)を注視しつつ壁待ち。",
    "buy_ratio": 63,
    "update_time": "2026-02-20 01:32"
}