{
    "price": 4938.0,
    "rsi": 29.18,
    "deviation": -1.12,
    "correlation": "Error",
    "score_1h": 39,
    "score_4h": 32,
    "is_golden": false,
    "is_death": false,
    "vol_spike": false,
    "trend_4h": "下落",
    "resistance": 5106.7,
    "support": 4875.2,
    "cisd_high": 4972.3,
    "cisd_low": 4997.4,
    "vacuum_zones": [
        {
            "from": 5121.5,
            "to": 5136.8
        }
    ],
    "is_synced": true,
    "sync_dir": "下落",
    "status": "✨ 期待値最大化ポイント",
    "reason": "長期下落と同方向に短期同期。加速の可能性あり。",
    "buy_ratio": 29,
    "update_time": "2026-02-17 22:53"
}